flake8_docstrings_complete/__init__.py
flake8_docstrings_complete/args.py
flake8_docstrings_complete/attrs.py
flake8_docstrings_complete/constants.py
flake8_docstrings_complete/docstring.py
flake8_docstrings_complete/raises.py
flake8_docstrings_complete/types_.py
flake8_docstrings_complete-1.4.1.dist-info/LICENSE
flake8_docstrings_complete-1.4.1.dist-info/METADATA
flake8_docstrings_complete-1.4.1.dist-info/WHEEL
flake8_docstrings_complete-1.4.1.dist-info/entry_points.txt
flake8_docstrings_complete-1.4.1.dist-info/RECORD
